tinydata-0.1.0.dist-info/METADATA
tinydata-0.1.0.dist-info/WHEEL
tinydata-0.1.0.dist-info/entry_points.txt
tinydata/__init__.py
tinydata/clip.py
tinydata/main.py
tinydata/tinydata.cpython-310-x86_64-linux-gnu.so
tinydata-0.1.0.dist-info/RECORD
