Metadata-Version: 2.3
Name: tinydata
Version: 0.1.0
Classifier: Programming Language :: Rust
Classifier: Programming Language :: Python :: Implementation :: CPython
Classifier: Programming Language :: Python :: Implementation :: PyPy
Requires-Dist: uvloop
Requires-Dist: open-clip-torch ==2.24.0 ; extra == 'ml'
Requires-Dist: pillow ; extra == 'ml'
Requires-Dist: progress ; extra == 'ml'
Provides-Extra: ml
Summary: A cli tool for building computer vision datasets.
License: MIT
Requires-Python: >=3.8
Project-URL: Source Code, https://github.com/nnethercott/tiny-data/tree/main
